didkit-0.3.3.dist-info/METADATA
didkit-0.3.3.dist-info/WHEEL
didkit-0.3.3.dist-info/license_files/LICENSE
didkit/py.typed
didkit/__init__.py
didkit/didkit.pyi
didkit/didkit.pypy39-pp73-x86-linux-gnu.so
didkit-0.3.3.dist-info/RECORD
