Metadata-Version: 2.1
Name: didkit
Version: 0.3.3
Classifier: Programming Language :: Rust
Classifier: Programming Language :: Python :: Implementation :: CPython
Classifier: Programming Language :: Python :: Implementation :: PyPy
Classifier: Topic :: Security
License-File: LICENSE
Summary: Library for Verifiable Credentials and Decentralized Identifiers.
Keywords: ssi,did,python
Home-Page: https://spruceid.dev/docs/didkit/
Author: Spruce Systems, Inc.
License: Apache-2.0
Requires-Python: >=3.7
Project-URL: Source Code, https://github.com/spruceid/didkit/
